{"ad-integration-pseudocode.md":"BD7EGv-h","api_api.md":"Cu_FtHUA","api_style.md":"BY84Imm6","api_tags.md":"Ch6jl_XR","api_tween.md":"C1HeKCxY","changelog.md":"BClIg6Ds","components_bitmapfont.md":"D8OA2Ob-","components_button.md":"BRFbegO3","components_canvas.md":"-owXjgmK","components_classlist.md":"DsTP5QmL","components_element.md":"C7pEEHPW","components_image.md":"CK2RIpcj","components_overview.md":"B06e31Jl","components_rect.md":"VIbjGRAO","components_scrollbar.md":"BddozqG_","components_scrollview.md":"tzJ9oXUR","components_text.md":"Brn83IUO","components_view.md":"Daq9zVog","demos_invite.md":"BZu9SsJ7","demos_rank.md":"Dz-ikgvs","index.md":"TKFJTLu1","indexxxx.md":"DcG-FPYZ","lobster-reskin-plan.md":"emkIc8G7","overview_guide.md":"CtcMoSQ0","overview_plugin.md":"DIu_R32G","plugin_guide.md":"Cdxs8tVV","plugin_richtext.md":"jWY06LMn","qa.md":"DFiEKHBd","tutorial_cocos2.x.md":"DpI7ddhR","tutorial_font.md":"XHBQb1O8","tutorial_loading.md":"HoV4FGIP","tutorial_platform.md":"nGiiyFdD","tutorial_style.md":"CHDcx0xo","tutorial_templateengine.md":"A9yrzVtY","tutorial_updateviewport.md":"BcpBys_W"}
